Workbook
Name in_revenue: Inputs!$B$5:$F$5
Name in_op_income: Inputs!$B$6:$F$6
Name in_da: Inputs!$B$7:$F$7
Name in_ebitda: Inputs!$B$8:$F$8
Name in_net_income: Inputs!$B$9:$F$9
Name in_cfo: Inputs!$B$10:$F$10
Name in_capex: Inputs!$B$11:$F$11
Name in_fcf: Inputs!$B$12:$F$12
Name in_interest_expense: Inputs!$B$13:$F$13
Name in_ufcf: Inputs!$B$14:$F$14
Name in_cash: Inputs!$B$15:$F$15
Name in_debt_total: Inputs!$B$16:$F$16
Name in_net_debt: Inputs!$B$17:$F$17
Name in_shares_diluted: Inputs!$B$18:$F$18
Name in_assets: Inputs!$B$19:$F$19
Name in_liab_equity: Inputs!$B$20:$F$20
Name in_equity: Inputs!$B$21:$F$21
Name in_fiscal_year: Inputs!$B$4:$F$4
Name Ticker: Inputs!$B$2
Name WACC: Inputs!$B$25
Name TermGrowth: Inputs!$B$26
Name FadeGrowth: Inputs!$B$27
Name StartGrowth: Inputs!$B$28
Name FCFMargin: Inputs!$B$29
Name TaxRate: Inputs!$B$30
Name Price: Inputs!$B$31
Name Sens_Grid: Sensitivity!$B$5:$F$13

Sheet Inputs
A1: Inputs (written by the pipeline; blue = hardcoded)
A2: Ticker
A4: Fiscal year
A5: Revenue
A6: Operating income
A7: Depreciation & amortization
A8: EBITDA (op. income + D&A) | B8: =IF(COUNT(B6,B7)=2,B6+B7,"") | C8: =IF(COUNT(C6,C7)=2,C6+C7,"") | D8: =IF(COUNT(D6,D7)=2,D6+D7,"") | E8: =IF(COUNT(E6,E7)=2,E6+E7,"") | F8: =IF(COUNT(F6,F7)=2,F6+F7,"")
A9: Net income
A10: Cash from operations
A11: Capital expenditures
A12: Free cash flow (CFO - capex) | B12: =IF(COUNT(B10,B11)=2,B10-B11,"") | C12: =IF(COUNT(C10,C11)=2,C10-C11,"") | D12: =IF(COUNT(D10,D11)=2,D10-D11,"") | E12: =IF(COUNT(E10,E11)=2,E10-E11,"") | F12: =IF(COUNT(F10,F11)=2,F10-F11,"")
A13: Interest expense
A14: Unlevered FCF (FCF + after-tax interest) | B14: =IF(COUNT(B10,B11)=2,B10-B11+N(B13)*(1-TaxRate),"") | C14: =IF(COUNT(C10,C11)=2,C10-C11+N(C13)*(1-TaxRate),"") | D14: =IF(COUNT(D10,D11)=2,D10-D11+N(D13)*(1-TaxRate),"") | E14: =IF(COUNT(E10,E11)=2,E10-E11+N(E13)*(1-TaxRate),"") | F14: =IF(COUNT(F10,F11)=2,F10-F11+N(F13)*(1-TaxRate),"")
A15: Cash & equivalents
A16: Total debt
A17: Net debt | B17: =IF(COUNT(B15)=1,B16-B15,"") | C17: =IF(COUNT(C15)=1,C16-C15,"") | D17: =IF(COUNT(D15)=1,D16-D15,"") | E17: =IF(COUNT(E15)=1,E16-E15,"") | F17: =IF(COUNT(F15)=1,F16-F15,"")
A18: Diluted shares (millions)
A19: Total assets
A20: Total liabilities & equity
A21: Stockholders' equity
A24: DCF assumptions (defaults derived from history; edit freely)
A25: WACC
A26: Terminal growth rate
A27: Year-5 revenue growth (fade target)
A28: Year-1 revenue growth
A29: Unlevered FCF margin
A30: Tax rate on interest
A31: Current share price ($)

Sheet IS
A1: Income statement summary
A3: USD millions unless noted | B3: =IF(Inputs!B4="","","FY"&Inputs!B4) | C3: =IF(Inputs!C4="","","FY"&Inputs!C4) | D3: =IF(Inputs!D4="","","FY"&Inputs!D4) | E3: =IF(Inputs!E4="","","FY"&Inputs!E4) | F3: =IF(Inputs!F4="","","FY"&Inputs!F4)
A4: Revenue | B4: =Inputs!B5 | C4: =Inputs!C5 | D4: =Inputs!D5 | E4: =Inputs!E5 | F4: =Inputs!F5
A5: growth % | C5: =IFERROR(C4/B4-1,"") | D5: =IFERROR(D4/C4-1,"") | E5: =IFERROR(E4/D4-1,"") | F5: =IFERROR(F4/E4-1,"")
A6: Operating income | B6: =Inputs!B6 | C6: =Inputs!C6 | D6: =Inputs!D6 | E6: =Inputs!E6 | F6: =Inputs!F6
A7: operating margin | B7: =IFERROR(B6/B4,"") | C7: =IFERROR(C6/C4,"") | D7: =IFERROR(D6/D4,"") | E7: =IFERROR(E6/E4,"") | F7: =IFERROR(F6/F4,"")
A8: D&A | B8: =Inputs!B7 | C8: =Inputs!C7 | D8: =Inputs!D7 | E8: =Inputs!E7 | F8: =Inputs!F7
A9: EBITDA | B9: =Inputs!B8 | C9: =Inputs!C8 | D9: =Inputs!D8 | E9: =Inputs!E8 | F9: =Inputs!F8
A10: EBITDA margin | B10: =IFERROR(B9/B4,"") | C10: =IFERROR(C9/C4,"") | D10: =IFERROR(D9/D4,"") | E10: =IFERROR(E9/E4,"") | F10: =IFERROR(F9/F4,"")
A11: Net income | B11: =Inputs!B9 | C11: =Inputs!C9 | D11: =Inputs!D9 | E11: =Inputs!E9 | F11: =Inputs!F9
A12: net margin | B12: =IFERROR(B11/B4,"") | C12: =IFERROR(C11/C4,"") | D12: =IFERROR(D11/D4,"") | E12: =IFERROR(E11/E4,"") | F12: =IFERROR(F11/F4,"")

Sheet BS
A1: Balance sheet summary
A3: USD millions unless noted | B3: =IF(Inputs!B4="","","FY"&Inputs!B4) | C3: =IF(Inputs!C4="","","FY"&Inputs!C4) | D3: =IF(Inputs!D4="","","FY"&Inputs!D4) | E3: =IF(Inputs!E4="","","FY"&Inputs!E4) | F3: =IF(Inputs!F4="","","FY"&Inputs!F4)
A4: Cash & equivalents | B4: =Inputs!B15 | C4: =Inputs!C15 | D4: =Inputs!D15 | E4: =Inputs!E15 | F4: =Inputs!F15
A5: Total assets | B5: =Inputs!B19 | C5: =Inputs!C19 | D5: =Inputs!D19 | E5: =Inputs!E19 | F5: =Inputs!F19
A6: Total liabilities | B6: =IF(COUNT(Inputs!B20,Inputs!B21)=2,Inputs!B20-Inputs!B21,"") | C6: =IF(COUNT(Inputs!C20,Inputs!C21)=2,Inputs!C20-Inputs!C21,"") | D6: =IF(COUNT(Inputs!D20,Inputs!D21)=2,Inputs!D20-Inputs!D21,"") | E6: =IF(COUNT(Inputs!E20,Inputs!E21)=2,Inputs!E20-Inputs!E21,"") | F6: =IF(COUNT(Inputs!F20,Inputs!F21)=2,Inputs!F20-Inputs!F21,"")
A7: Stockholders' equity | B7: =Inputs!B21 | C7: =Inputs!C21 | D7: =Inputs!D21 | E7: =Inputs!E21 | F7: =Inputs!F21
A8: Total liabilities & equity | B8: =Inputs!B20 | C8: =Inputs!C20 | D8: =Inputs!D20 | E8: =Inputs!E20 | F8: =Inputs!F20
A9: Balance check (assets - L&E) | B9: =IF(COUNT(B5,B8)=2,B5-B8,"") | C9: =IF(COUNT(C5,C8)=2,C5-C8,"") | D9: =IF(COUNT(D5,D8)=2,D5-D8,"") | E9: =IF(COUNT(E5,E8)=2,E5-E8,"") | F9: =IF(COUNT(F5,F8)=2,F5-F8,"")
A10: Total debt | B10: =Inputs!B16 | C10: =Inputs!C16 | D10: =Inputs!D16 | E10: =Inputs!E16 | F10: =Inputs!F16
A11: Net debt | B11: =Inputs!B17 | C11: =Inputs!C17 | D11: =Inputs!D17 | E11: =Inputs!E17 | F11: =Inputs!F17
A12: Net debt / EBITDA (x) | B12: =IFERROR(IF(IS!B9>0,B11/IS!B9,""),"") | C12: =IFERROR(IF(IS!C9>0,C11/IS!C9,""),"") | D12: =IFERROR(IF(IS!D9>0,D11/IS!D9,""),"") | E12: =IFERROR(IF(IS!E9>0,E11/IS!E9,""),"") | F12: =IFERROR(IF(IS!F9>0,F11/IS!F9,""),"")

Sheet CF
A1: Cash flow summary
A3: USD millions unless noted | B3: =IF(Inputs!B4="","","FY"&Inputs!B4) | C3: =IF(Inputs!C4="","","FY"&Inputs!C4) | D3: =IF(Inputs!D4="","","FY"&Inputs!D4) | E3: =IF(Inputs!E4="","","FY"&Inputs!E4) | F3: =IF(Inputs!F4="","","FY"&Inputs!F4)
A4: Cash from operations | B4: =Inputs!B10 | C4: =Inputs!C10 | D4: =Inputs!D10 | E4: =Inputs!E10 | F4: =Inputs!F10
A5: Capital expenditures | B5: =Inputs!B11 | C5: =Inputs!C11 | D5: =Inputs!D11 | E5: =Inputs!E11 | F5: =Inputs!F11
A6: Free cash flow | B6: =Inputs!B12 | C6: =Inputs!C12 | D6: =Inputs!D12 | E6: =Inputs!E12 | F6: =Inputs!F12
A7: FCF margin | B7: =IFERROR(B6/IS!B4,"") | C7: =IFERROR(C6/IS!C4,"") | D7: =IFERROR(D6/IS!D4,"") | E7: =IFERROR(E6/IS!E4,"") | F7: =IFERROR(F6/IS!F4,"")
A8: FCF conversion (FCF / net income) | B8: =IFERROR(B6/IS!B11,"") | C8: =IFERROR(C6/IS!C11,"") | D8: =IFERROR(D6/IS!D11,"") | E8: =IFERROR(E6/IS!E11,"") | F8: =IFERROR(F6/IS!F11,"")
A9: Interest expense | B9: =Inputs!B13 | C9: =Inputs!C13 | D9: =Inputs!D13 | E9: =Inputs!E13 | F9: =Inputs!F13
A10: Unlevered FCF | B10: =Inputs!B14 | C10: =Inputs!C14 | D10: =Inputs!D14 | E10: =Inputs!E14 | F10: =Inputs!F14

Sheet DCF
A1: Five-year DCF (live formulas; driven by named assumptions on Inputs)
A2: USD millions unless noted | B2: Year 1 | C2: Year 2 | D2: Year 3 | E2: Year 4 | F2: Year 5
A3: Projection year | B3: 1 | C3: 2 | D3: 3 | E3: 4 | F3: 5
A4: Revenue growth | B4: =StartGrowth+(FadeGrowth-StartGrowth)*(B3-1)/4 | C4: =StartGrowth+(FadeGrowth-StartGrowth)*(C3-1)/4 | D4: =StartGrowth+(FadeGrowth-StartGrowth)*(D3-1)/4 | E4: =StartGrowth+(FadeGrowth-StartGrowth)*(E3-1)/4 | F4: =StartGrowth+(FadeGrowth-StartGrowth)*(F3-1)/4
A5: Revenue | B5: =Inputs!F5*(1+B4) | C5: =B5*(1+C4) | D5: =C5*(1+D4) | E5: =D5*(1+E4) | F5: =E5*(1+F4)
A6: Unlevered FCF margin | B6: =FCFMargin | C6: =FCFMargin | D6: =FCFMargin | E6: =FCFMargin | F6: =FCFMargin
A7: Unlevered FCF | B7: =B5*B6 | C7: =C5*C6 | D7: =D5*D6 | E7: =E5*E6 | F7: =F5*F6
A8: Discount factor | B8: =1/(1+WACC)^B3 | C8: =1/(1+WACC)^C3 | D8: =1/(1+WACC)^D3 | E8: =1/(1+WACC)^E3 | F8: =1/(1+WACC)^F3
A9: PV of FCF | B9: =B7*B8 | C9: =C7*C8 | D9: =D7*D8 | E9: =E7*E8 | F9: =F7*F8
A11: Sum of PV of FCF | B11: =SUM(B9:F9)
A12: Terminal value (Gordon growth) | B12: =F7*(1+TermGrowth)/(WACC-TermGrowth)
A13: PV of terminal value | B13: =B12*F8
A14: Enterprise value | B14: =B11+B13
A15: Less: net debt (latest FY) | B15: =N(Inputs!F17)
A16: Equity value | B16: =B14-B15
A17: Diluted shares (millions) | B17: =N(Inputs!F18)
A18: Equity value per share ($) | B18: =IF(AND(B17>0,ISNUMBER(FCFMargin),WACC>TermGrowth),B16/B17,"n/a")
A19: Current price ($) | B19: =Price
A20: Upside / (downside) | B20: =IF(AND(ISNUMBER(B18),N(Price)>0),B18/Price-1,"n/a")
A21: Terminal value as % of EV | B21: =IFERROR(B13/B14,"n/a")

Sheet Sensitivity
A1: Equity value per share ($): WACC (rows) x terminal growth (columns)
A2: Current price | B2: =Price
A3: Green = at/above current price; red = below. Headers are editable inputs.
A4: WACC \ g | B4: 0.01 | C4: 0.015 | D4: 0.02 | E4: 0.025 | F4: 0.03
A5: 0.07 | B5: =IF(AND(N(Inputs!$F$18)>0,ISNUMBER(FCFMargin),$A5>B$4),(SUMPRODUCT(DCF!$B$7:$F$7/(1+$A5)^DCF!$B$3:$F$3)+DCF!$F$7*(1+B$4)/($A5-B$4)/(1+$A5)^DCF!$F$3-DCF!$B$15)/DCF!$B$17,"n/a") | C5: =IF(AND(N(Inputs!$F$18)>0,ISNUMBER(FCFMargin),$A5>C$4),(SUMPRODUCT(DCF!$B$7:$F$7/(1+$A5)^DCF!$B$3:$F$3)+DCF!$F$7*(1+C$4)/($A5-C$4)/(1+$A5)^DCF!$F$3-DCF!$B$15)/DCF!$B$17,"n/a") | D5: =IF(AND(N(Inputs!$F$18)>0,ISNUMBER(FCFMargin),$A5>D$4),(SUMPRODUCT(DCF!$B$7:$F$7/(1+$A5)^DCF!$B$3:$F$3)+DCF!$F$7*(1+D$4)/($A5-D$4)/(1+$A5)^DCF!$F$3-DCF!$B$15)/DCF!$B$17,"n/a") | E5: =IF(AND(N(Inputs!$F$18)>0,ISNUMBER(FCFMargin),$A5>E$4),(SUMPRODUCT(DCF!$B$7:$F$7/(1+$A5)^DCF!$B$3:$F$3)+DCF!$F$7*(1+E$4)/($A5-E$4)/(1+$A5)^DCF!$F$3-DCF!$B$15)/DCF!$B$17,"n/a") | F5: =IF(AND(N(Inputs!$F$18)>0,ISNUMBER(FCFMargin),$A5>F$4),(SUMPRODUCT(DCF!$B$7:$F$7/(1+$A5)^DCF!$B$3:$F$3)+DCF!$F$7*(1+F$4)/($A5-F$4)/(1+$A5)^DCF!$F$3-DCF!$B$15)/DCF!$B$17,"n/a")
A6: 0.075 | B6: =IF(AND(N(Inputs!$F$18)>0,ISNUMBER(FCFMargin),$A6>B$4),(SUMPRODUCT(DCF!$B$7:$F$7/(1+$A6)^DCF!$B$3:$F$3)+DCF!$F$7*(1+B$4)/($A6-B$4)/(1+$A6)^DCF!$F$3-DCF!$B$15)/DCF!$B$17,"n/a") | C6: =IF(AND(N(Inputs!$F$18)>0,ISNUMBER(FCFMargin),$A6>C$4),(SUMPRODUCT(DCF!$B$7:$F$7/(1+$A6)^DCF!$B$3:$F$3)+DCF!$F$7*(1+C$4)/($A6-C$4)/(1+$A6)^DCF!$F$3-DCF!$B$15)/DCF!$B$17,"n/a") | D6: =IF(AND(N(Inputs!$F$18)>0,ISNUMBER(FCFMargin),$A6>D$4),(SUMPRODUCT(DCF!$B$7:$F$7/(1+$A6)^DCF!$B$3:$F$3)+DCF!$F$7*(1+D$4)/($A6-D$4)/(1+$A6)^DCF!$F$3-DCF!$B$15)/DCF!$B$17,"n/a") | E6: =IF(AND(N(Inputs!$F$18)>0,ISNUMBER(FCFMargin),$A6>E$4),(SUMPRODUCT(DCF!$B$7:$F$7/(1+$A6)^DCF!$B$3:$F$3)+DCF!$F$7*(1+E$4)/($A6-E$4)/(1+$A6)^DCF!$F$3-DCF!$B$15)/DCF!$B$17,"n/a") | F6: =IF(AND(N(Inputs!$F$18)>0,ISNUMBER(FCFMargin),$A6>F$4),(SUMPRODUCT(DCF!$B$7:$F$7/(1+$A6)^DCF!$B$3:$F$3)+DCF!$F$7*(1+F$4)/($A6-F$4)/(1+$A6)^DCF!$F$3-DCF!$B$15)/DCF!$B$17,"n/a")
A7: 0.08 | B7: =IF(AND(N(Inputs!$F$18)>0,ISNUMBER(FCFMargin),$A7>B$4),(SUMPRODUCT(DCF!$B$7:$F$7/(1+$A7)^DCF!$B$3:$F$3)+DCF!$F$7*(1+B$4)/($A7-B$4)/(1+$A7)^DCF!$F$3-DCF!$B$15)/DCF!$B$17,"n/a") | C7: =IF(AND(N(Inputs!$F$18)>0,ISNUMBER(FCFMargin),$A7>C$4),(SUMPRODUCT(DCF!$B$7:$F$7/(1+$A7)^DCF!$B$3:$F$3)+DCF!$F$7*(1+C$4)/($A7-C$4)/(1+$A7)^DCF!$F$3-DCF!$B$15)/DCF!$B$17,"n/a") | D7: =IF(AND(N(Inputs!$F$18)>0,ISNUMBER(FCFMargin),$A7>D$4),(SUMPRODUCT(DCF!$B$7:$F$7/(1+$A7)^DCF!$B$3:$F$3)+DCF!$F$7*(1+D$4)/($A7-D$4)/(1+$A7)^DCF!$F$3-DCF!$B$15)/DCF!$B$17,"n/a") | E7: =IF(AND(N(Inputs!$F$18)>0,ISNUMBER(FCFMargin),$A7>E$4),(SUMPRODUCT(DCF!$B$7:$F$7/(1+$A7)^DCF!$B$3:$F$3)+DCF!$F$7*(1+E$4)/($A7-E$4)/(1+$A7)^DCF!$F$3-DCF!$B$15)/DCF!$B$17,"n/a") | F7: =IF(AND(N(Inputs!$F$18)>0,ISNUMBER(FCFMargin),$A7>F$4),(SUMPRODUCT(DCF!$B$7:$F$7/(1+$A7)^DCF!$B$3:$F$3)+DCF!$F$7*(1+F$4)/($A7-F$4)/(1+$A7)^DCF!$F$3-DCF!$B$15)/DCF!$B$17,"n/a")
A8: 0.085 | B8: =IF(AND(N(Inputs!$F$18)>0,ISNUMBER(FCFMargin),$A8>B$4),(SUMPRODUCT(DCF!$B$7:$F$7/(1+$A8)^DCF!$B$3:$F$3)+DCF!$F$7*(1+B$4)/($A8-B$4)/(1+$A8)^DCF!$F$3-DCF!$B$15)/DCF!$B$17,"n/a") | C8: =IF(AND(N(Inputs!$F$18)>0,ISNUMBER(FCFMargin),$A8>C$4),(SUMPRODUCT(DCF!$B$7:$F$7/(1+$A8)^DCF!$B$3:$F$3)+DCF!$F$7*(1+C$4)/($A8-C$4)/(1+$A8)^DCF!$F$3-DCF!$B$15)/DCF!$B$17,"n/a") | D8: =IF(AND(N(Inputs!$F$18)>0,ISNUMBER(FCFMargin),$A8>D$4),(SUMPRODUCT(DCF!$B$7:$F$7/(1+$A8)^DCF!$B$3:$F$3)+DCF!$F$7*(1+D$4)/($A8-D$4)/(1+$A8)^DCF!$F$3-DCF!$B$15)/DCF!$B$17,"n/a") | E8: =IF(AND(N(Inputs!$F$18)>0,ISNUMBER(FCFMargin),$A8>E$4),(SUMPRODUCT(DCF!$B$7:$F$7/(1+$A8)^DCF!$B$3:$F$3)+DCF!$F$7*(1+E$4)/($A8-E$4)/(1+$A8)^DCF!$F$3-DCF!$B$15)/DCF!$B$17,"n/a") | F8: =IF(AND(N(Inputs!$F$18)>0,ISNUMBER(FCFMargin),$A8>F$4),(SUMPRODUCT(DCF!$B$7:$F$7/(1+$A8)^DCF!$B$3:$F$3)+DCF!$F$7*(1+F$4)/($A8-F$4)/(1+$A8)^DCF!$F$3-DCF!$B$15)/DCF!$B$17,"n/a")
A9: 0.09 | B9: =IF(AND(N(Inputs!$F$18)>0,ISNUMBER(FCFMargin),$A9>B$4),(SUMPRODUCT(DCF!$B$7:$F$7/(1+$A9)^DCF!$B$3:$F$3)+DCF!$F$7*(1+B$4)/($A9-B$4)/(1+$A9)^DCF!$F$3-DCF!$B$15)/DCF!$B$17,"n/a") | C9: =IF(AND(N(Inputs!$F$18)>0,ISNUMBER(FCFMargin),$A9>C$4),(SUMPRODUCT(DCF!$B$7:$F$7/(1+$A9)^DCF!$B$3:$F$3)+DCF!$F$7*(1+C$4)/($A9-C$4)/(1+$A9)^DCF!$F$3-DCF!$B$15)/DCF!$B$17,"n/a") | D9: =IF(AND(N(Inputs!$F$18)>0,ISNUMBER(FCFMargin),$A9>D$4),(SUMPRODUCT(DCF!$B$7:$F$7/(1+$A9)^DCF!$B$3:$F$3)+DCF!$F$7*(1+D$4)/($A9-D$4)/(1+$A9)^DCF!$F$3-DCF!$B$15)/DCF!$B$17,"n/a") | E9: =IF(AND(N(Inputs!$F$18)>0,ISNUMBER(FCFMargin),$A9>E$4),(SUMPRODUCT(DCF!$B$7:$F$7/(1+$A9)^DCF!$B$3:$F$3)+DCF!$F$7*(1+E$4)/($A9-E$4)/(1+$A9)^DCF!$F$3-DCF!$B$15)/DCF!$B$17,"n/a") | F9: =IF(AND(N(Inputs!$F$18)>0,ISNUMBER(FCFMargin),$A9>F$4),(SUMPRODUCT(DCF!$B$7:$F$7/(1+$A9)^DCF!$B$3:$F$3)+DCF!$F$7*(1+F$4)/($A9-F$4)/(1+$A9)^DCF!$F$3-DCF!$B$15)/DCF!$B$17,"n/a")
A10: 0.095 | B10: =IF(AND(N(Inputs!$F$18)>0,ISNUMBER(FCFMargin),$A10>B$4),(SUMPRODUCT(DCF!$B$7:$F$7/(1+$A10)^DCF!$B$3:$F$3)+DCF!$F$7*(1+B$4)/($A10-B$4)/(1+$A10)^DCF!$F$3-DCF!$B$15)/DCF!$B$17,"n/a") | C10: =IF(AND(N(Inputs!$F$18)>0,ISNUMBER(FCFMargin),$A10>C$4),(SUMPRODUCT(DCF!$B$7:$F$7/(1+$A10)^DCF!$B$3:$F$3)+DCF!$F$7*(1+C$4)/($A10-C$4)/(1+$A10)^DCF!$F$3-DCF!$B$15)/DCF!$B$17,"n/a") | D10: =IF(AND(N(Inputs!$F$18)>0,ISNUMBER(FCFMargin),$A10>D$4),(SUMPRODUCT(DCF!$B$7:$F$7/(1+$A10)^DCF!$B$3:$F$3)+DCF!$F$7*(1+D$4)/($A10-D$4)/(1+$A10)^DCF!$F$3-DCF!$B$15)/DCF!$B$17,"n/a") | E10: =IF(AND(N(Inputs!$F$18)>0,ISNUMBER(FCFMargin),$A10>E$4),(SUMPRODUCT(DCF!$B$7:$F$7/(1+$A10)^DCF!$B$3:$F$3)+DCF!$F$7*(1+E$4)/($A10-E$4)/(1+$A10)^DCF!$F$3-DCF!$B$15)/DCF!$B$17,"n/a") | F10: =IF(AND(N(Inputs!$F$18)>0,ISNUMBER(FCFMargin),$A10>F$4),(SUMPRODUCT(DCF!$B$7:$F$7/(1+$A10)^DCF!$B$3:$F$3)+DCF!$F$7*(1+F$4)/($A10-F$4)/(1+$A10)^DCF!$F$3-DCF!$B$15)/DCF!$B$17,"n/a")
A11: 0.1 | B11: =IF(AND(N(Inputs!$F$18)>0,ISNUMBER(FCFMargin),$A11>B$4),(SUMPRODUCT(DCF!$B$7:$F$7/(1+$A11)^DCF!$B$3:$F$3)+DCF!$F$7*(1+B$4)/($A11-B$4)/(1+$A11)^DCF!$F$3-DCF!$B$15)/DCF!$B$17,"n/a") | C11: =IF(AND(N(Inputs!$F$18)>0,ISNUMBER(FCFMargin),$A11>C$4),(SUMPRODUCT(DCF!$B$7:$F$7/(1+$A11)^DCF!$B$3:$F$3)+DCF!$F$7*(1+C$4)/($A11-C$4)/(1+$A11)^DCF!$F$3-DCF!$B$15)/DCF!$B$17,"n/a") | D11: =IF(AND(N(Inputs!$F$18)>0,ISNUMBER(FCFMargin),$A11>D$4),(SUMPRODUCT(DCF!$B$7:$F$7/(1+$A11)^DCF!$B$3:$F$3)+DCF!$F$7*(1+D$4)/($A11-D$4)/(1+$A11)^DCF!$F$3-DCF!$B$15)/DCF!$B$17,"n/a") | E11: =IF(AND(N(Inputs!$F$18)>0,ISNUMBER(FCFMargin),$A11>E$4),(SUMPRODUCT(DCF!$B$7:$F$7/(1+$A11)^DCF!$B$3:$F$3)+DCF!$F$7*(1+E$4)/($A11-E$4)/(1+$A11)^DCF!$F$3-DCF!$B$15)/DCF!$B$17,"n/a") | F11: =IF(AND(N(Inputs!$F$18)>0,ISNUMBER(FCFMargin),$A11>F$4),(SUMPRODUCT(DCF!$B$7:$F$7/(1+$A11)^DCF!$B$3:$F$3)+DCF!$F$7*(1+F$4)/($A11-F$4)/(1+$A11)^DCF!$F$3-DCF!$B$15)/DCF!$B$17,"n/a")
A12: 0.105 | B12: =IF(AND(N(Inputs!$F$18)>0,ISNUMBER(FCFMargin),$A12>B$4),(SUMPRODUCT(DCF!$B$7:$F$7/(1+$A12)^DCF!$B$3:$F$3)+DCF!$F$7*(1+B$4)/($A12-B$4)/(1+$A12)^DCF!$F$3-DCF!$B$15)/DCF!$B$17,"n/a") | C12: =IF(AND(N(Inputs!$F$18)>0,ISNUMBER(FCFMargin),$A12>C$4),(SUMPRODUCT(DCF!$B$7:$F$7/(1+$A12)^DCF!$B$3:$F$3)+DCF!$F$7*(1+C$4)/($A12-C$4)/(1+$A12)^DCF!$F$3-DCF!$B$15)/DCF!$B$17,"n/a") | D12: =IF(AND(N(Inputs!$F$18)>0,ISNUMBER(FCFMargin),$A12>D$4),(SUMPRODUCT(DCF!$B$7:$F$7/(1+$A12)^DCF!$B$3:$F$3)+DCF!$F$7*(1+D$4)/($A12-D$4)/(1+$A12)^DCF!$F$3-DCF!$B$15)/DCF!$B$17,"n/a") | E12: =IF(AND(N(Inputs!$F$18)>0,ISNUMBER(FCFMargin),$A12>E$4),(SUMPRODUCT(DCF!$B$7:$F$7/(1+$A12)^DCF!$B$3:$F$3)+DCF!$F$7*(1+E$4)/($A12-E$4)/(1+$A12)^DCF!$F$3-DCF!$B$15)/DCF!$B$17,"n/a") | F12: =IF(AND(N(Inputs!$F$18)>0,ISNUMBER(FCFMargin),$A12>F$4),(SUMPRODUCT(DCF!$B$7:$F$7/(1+$A12)^DCF!$B$3:$F$3)+DCF!$F$7*(1+F$4)/($A12-F$4)/(1+$A12)^DCF!$F$3-DCF!$B$15)/DCF!$B$17,"n/a")
A13: 0.11 | B13: =IF(AND(N(Inputs!$F$18)>0,ISNUMBER(FCFMargin),$A13>B$4),(SUMPRODUCT(DCF!$B$7:$F$7/(1+$A13)^DCF!$B$3:$F$3)+DCF!$F$7*(1+B$4)/($A13-B$4)/(1+$A13)^DCF!$F$3-DCF!$B$15)/DCF!$B$17,"n/a") | C13: =IF(AND(N(Inputs!$F$18)>0,ISNUMBER(FCFMargin),$A13>C$4),(SUMPRODUCT(DCF!$B$7:$F$7/(1+$A13)^DCF!$B$3:$F$3)+DCF!$F$7*(1+C$4)/($A13-C$4)/(1+$A13)^DCF!$F$3-DCF!$B$15)/DCF!$B$17,"n/a") | D13: =IF(AND(N(Inputs!$F$18)>0,ISNUMBER(FCFMargin),$A13>D$4),(SUMPRODUCT(DCF!$B$7:$F$7/(1+$A13)^DCF!$B$3:$F$3)+DCF!$F$7*(1+D$4)/($A13-D$4)/(1+$A13)^DCF!$F$3-DCF!$B$15)/DCF!$B$17,"n/a") | E13: =IF(AND(N(Inputs!$F$18)>0,ISNUMBER(FCFMargin),$A13>E$4),(SUMPRODUCT(DCF!$B$7:$F$7/(1+$A13)^DCF!$B$3:$F$3)+DCF!$F$7*(1+E$4)/($A13-E$4)/(1+$A13)^DCF!$F$3-DCF!$B$15)/DCF!$B$17,"n/a") | F13: =IF(AND(N(Inputs!$F$18)>0,ISNUMBER(FCFMargin),$A13>F$4),(SUMPRODUCT(DCF!$B$7:$F$7/(1+$A13)^DCF!$B$3:$F$3)+DCF!$F$7*(1+F$4)/($A13-F$4)/(1+$A13)^DCF!$F$3-DCF!$B$15)/DCF!$B$17,"n/a")
